Workbook

Sheet Cover
A1: Model Title: [Engagement codename] - Opportunity Model
A2: STARTER TEMPLATE - example logic and example inputs. Replace before use.
A4: Purpose | B4: Size the EBITDA opportunity and 5-year value of three initiatives; test scenarios and sensitivities.
A5: Question 1 | B5: What is the baseline, and does it tie to the client ledger?
A6: Question 2 | B6: What run-rate EBITDA does each initiative create under Low / Base / High?
A7: Question 3 | B7: What is the NPV and payback, and which assumption moves the answer most?
A8: Owner | B8: [Model owner name]
A9: Reviewer | B9: [Independent reviewer name]
A10: Version / status | B10: v0.1 - Template
A11: Date | B11: 2026-10-16
A12: File name convention | B12: [Model]_[STATUS]_[vYYYYMMDD]_[initials].xlsx
A13: Active scenario | B13: =Scenarios!C4 -> Base
A15: Master check
A16: Integrity flags | C16: =Checks!C21 -> 0
A17: Sense-check flags | C17: =Checks!C22 -> 0
A18: Status | B18: =IF(C16=0,"ALL INTEGRITY CHECKS OK","ERRORS: "&C16&" integrity check(s) flagged") -> ALL INTEGRITY CHECKS OK
A20: Contents
A21: Guide | B21: How to use and adapt
A22: Inputs | B22: All assumptions, sourced
A23: Data_Raw | B23: Untouched client data
A24: Calc | B24: Calculations
A25: Scenarios | B25: Scenario selector
A26: Outputs | B26: Numbers for slides; bridge
A27: Checks | B27: Integrity and sense checks
A28: Log | B28: Versions, data, issues, sign-off
A30: Color key
A31: 1,234.5 | B31: Blue font: hard-coded input
A32: 1,234.5 | B32: Black font: formula
A33: 1,234.5 | B33: Green font: pulled from another tab
A34: Base | B34: Yellow fill: key selector
A35: 0 | B35: Green fill: check passes
A36: 1 | B36: Red fill: check flagged

Sheet Guide
A1: Guide
A2: How this starter model is organized and how to adapt it.
A4: Purpose | B4: Starter structure for a consulting-style opportunity model: inputs, calculations, scenarios, outputs, checks, and a log. The example sizes three initiatives and a simple 5-year business case. Replace the example logic, keep the structure.
A5: Flow | B5: Inputs -> Calc -> Outputs. Checks reads from everywhere. Scenarios chooses the live column on Inputs.
A6: Inputs tab | B6: One row per assumption with unit, Low/Base/High, source, owner, date, confidence. The 'Live' column picks the active scenario. Never type a number inside a formula elsewhere.
A7: Calc tab | B7: Block A pulls inputs (green). Block B computes run-rate. Block C is the time series. One formula per row, copied across all periods.
A8: Outputs tab | B8: Every number that goes on a slide. Add the slide number in 'Used on slide(s)'. The bridge block feeds the waterfall chart.
A9: Checks tab | B9: Integrity checks must be zero. Sense checks flag for review. The master check shows on the Cover.
A10: Log tab | B10: Record each version, each data pull, open issues, and reviewer sign-off.
A11: To adapt | B11: 1) Write the three questions on the Cover. 2) Replace Inputs rows. 3) Rebuild Calc blocks B and C for your logic. 4) Update Outputs and Checks. 5) Get an independent review before any number goes to the client.
A12: Color key | B12: Blue font = hard-coded input. Black = formula. Green = pulled from another tab. Yellow fill = key selector. Pale yellow fill = input cell. Change this convention only if the client or firm template requires it, and update the Cover.
A13: Rules | B13: No hard-codes in formulas (only 0, 1, -1). One formula per row. No merged cells. No OFFSET or INDIRECT. No circular references. Units on every line. Negatives in brackets.
A14: Model owner | B14: One person holds the master. Everyone else works on a copy and sends changes to the owner.
A15: Formulas used | B15: INDEX, MATCH, SUM, IF, MAX, ABS, SUMPRODUCT, COUNT. Chosen to work in Excel, Google Sheets, and LibreOffice.

Sheet Inputs
A1: Inputs
A2: Every assumption lives here, once. Blue = hard-coded input. Black = formula. EXAMPLE values: replace with real, sourced inputs.
B4: Scenario index (linked) | C4: =Scenarios!C5 -> 2
A7: Ref | B7: Input | C7: Unit | D7: Low | E7: Base | F7: High | G7: Live | H7: Source | I7: Owner | J7: Date | K7: Confidence
A8: I1 | B8: Baseline revenue | C8: $M | D8: 610 | E8: 610 | F8: 610 | G8: =INDEX(D8:F8,$C$4) -> 610 | H8: EXAMPLE: FY26 audited P&L | I8: CFO office | J8: 2026-10-16 | K8: High
A9: I2 | B9: Baseline EBITDA margin | C9: % of revenue | D9: 0.15 | E9: 0.15 | F9: 0.15 | G9: =INDEX(D9:F9,$C$4) -> 0.15 | H9: EXAMPLE: FY26 audited P&L | I9: CFO office | J9: 2026-10-16 | K9: High
A10: I3 | B10: Client-reported baseline EBITDA (for tie-out) | C10: $M | D10: 91.5 | E10: 91.5 | F10: 91.5 | G10: =INDEX(D10:F10,$C$4) -> 91.5 | H10: EXAMPLE: FY26 annual report | I10: CFO office | J10: 2026-10-16 | K10: High
A11: I4 | B11: Check tolerance | C11: $M | D11: 0.05 | E11: 0.05 | F11: 0.05 | G11: =INDEX(D11:F11,$C$4) -> 0.05 | H11: Team standard | I11: Model owner | J11: 2026-10-16 | K11: High
A12: I5 | B12: Initiative 1: revenue uplift | C12: % of baseline revenue | D12: 0.01 | E12: 0.02 | F12: 0.03 | G12: =INDEX(D12:F12,$C$4) -> 0.02 | H12: EXAMPLE: pilot results + benchmark | I12: Consultant 1 | J12: 2026-10-16 | K12: Medium
A13: I6 | B13: Initiative 1: EBITDA flow-through | C13: % of added revenue | D13: 0.4 | E13: 0.4 | F13: 0.4 | G13: =INDEX(D13:F13,$C$4) -> 0.4 | H13: EXAMPLE: contribution margin analysis | I13: Consultant 1 | J13: 2026-10-16 | K13: Medium
A14: I7 | B14: Initiative 2: cost reduction | C14: % of baseline cost | D14: 0.005 | E14: 0.01 | F14: 0.015 | G14: =INDEX(D14:F14,$C$4) -> 0.01 | H14: EXAMPLE: spend cube + peer benchmark | I14: Consultant 2 | J14: 2026-10-16 | K14: Medium
A15: I8 | B15: Initiative 3: price realization | C15: % of baseline revenue | D15: 0.003 | E15: 0.006 | F15: 0.009 | G15: =INDEX(D15:F15,$C$4) -> 0.006 | H15: EXAMPLE: leakage analysis, 14 sites | I15: Analyst | J15: 2026-10-16 | K15: Low
A16: I9 | B16: Initiative 3: EBITDA flow-through | C16: % of added revenue | D16: 0.9 | E16: 0.9 | F16: 0.9 | G16: =INDEX(D16:F16,$C$4) -> 0.9 | H16: EXAMPLE: pricing team | I16: Analyst | J16: 2026-10-16 | K16: Medium
A17: I10 | B17: Total one-time cost | C17: $M | D17: 8 | E17: 6 | F17: 4 | G17: =INDEX(D17:F17,$C$4) -> 6 | H17: EXAMPLE: vendor quotes + internal estimate | I17: Consultant 2 | J17: 2026-10-16 | K17: Low
A18: I11 | B18: Discount rate | C18: % | D18: 0.1 | E18: 0.1 | F18: 0.1 | G18: =INDEX(D18:F18,$C$4) -> 0.1 | H18: EXAMPLE: client WACC memo | I18: CFO office | J18: 2026-10-16 | K18: Medium
A20: Time-series inputs (same in every scenario)
A21: Ref | B21: Input | C21: Unit | D21: Y1 | E21: Y2 | F21: Y3 | G21: Y4 | H21: Y5 | I21: Total / Max
A22: T1 | B22: Ramp-up (share of run-rate achieved) | C22: % of run-rate | D22: 0.2 | E22: 0.5 | F22: 0.8 | G22: 1 | H22: 1 | I22: =MAX(D22:H22) -> 1
A23: T2 | B23: One-time cost phasing | C23: % of total cost | D23: 0.6 | E23: 0.4 | F23: 0 | G23: 0 | H23: 0 | I23: =SUM(D23:H23) -> 1

Sheet Data_Raw
A1: Data_Raw
A2: Paste raw client data here, untouched. Clean in a separate tab or in Power Query. Log every pull on the Log tab.
A4: Property | B4: Month | C4: Channel | D4: Room nights | E4: Revenue ($)
A5: P001 | B5: 2026-01 | C5: OTA | D5: 4120 | E5: 612400
A6: P001 | B6: 2026-01 | C6: Direct | D6: 2210 | E6: 351800
A7: P002 | B7: 2026-01 | C7: OTA | D7: 3380 | E7: 498100
A9: Source: EXAMPLE rows only. Replace with client export. Record file name, date, owner, and permission basis on the Log tab.

Sheet Calc
A1: Calc
A2: Flows top to bottom. Green = pulled from another tab. Black = calculation. One formula per row, copied across.
A4: Line item | B4: Unit | C4: Constant / Total | D4: Y1 | E4: Y2 | F4: Y3 | G4: Y4 | H4: Y5
A5: Year number | B5: # | D5: 1 | E5: =D5+1 -> 2 | F5: =E5+1 -> 3 | G5: =F5+1 -> 4 | H5: =G5+1 -> 5
A7: A. Linked inputs
A8: Baseline revenue | B8: $M | C8: =Inputs!G8 -> 610
A9: Baseline EBITDA margin | B9: % | C9: =Inputs!G9 -> 0.15
A10: Initiative 1 revenue uplift | B10: % | C10: =Inputs!G12 -> 0.02
A11: Initiative 1 flow-through | B11: % | C11: =Inputs!G13 -> 0.4
A12: Initiative 2 cost reduction | B12: % | C12: =Inputs!G14 -> 0.01
A13: Initiative 3 price realization | B13: % | C13: =Inputs!G15 -> 0.006
A14: Initiative 3 flow-through | B14: % | C14: =Inputs!G16 -> 0.9
A15: Total one-time cost | B15: $M | C15: =Inputs!G17 -> 6
A16: Discount rate | B16: % | C16: =Inputs!G18 -> 0.1
A17: Ramp-up | B17: % | D17: =Inputs!D22 -> 0.2 | E17: =Inputs!E22 -> 0.5 | F17: =Inputs!F22 -> 0.8 | G17: =Inputs!G22 -> 1 | H17: =Inputs!H22 -> 1
A18: One-time cost phasing | B18: % | D18: =Inputs!D23 -> 0.6 | E18: =Inputs!E23 -> 0.4 | F18: =Inputs!F23 -> 0 | G18: =Inputs!G23 -> 0 | H18: =Inputs!H23 -> 0
A20: B. Run-rate economics
A21: Baseline EBITDA | B21: $M | C21: =C8*C9 -> 91.5
A22: Baseline cost base | B22: $M | C22: =C8-C21 -> 518.5
A23: Initiative 1 run-rate EBITDA | B23: $M | C23: =C8*C10*C11 -> 4.88
A24: Initiative 2 run-rate EBITDA | B24: $M | C24: =C22*C12 -> 5.185
A25: Initiative 3 run-rate EBITDA | B25: $M | C25: =C8*C13*C14 -> 3.294
A26: Total run-rate EBITDA uplift | B26: $M | C26: =SUM(C23:C25) -> 13.359
A28: C. Time series
A29: Initiative 1 benefit | B29: $M | C29: =SUM(D29:H29) -> 17.08 | D29: =$C$23*D$17 -> 0.976 | E29: =$C$23*E$17 -> 2.44 | F29: =$C$23*F$17 -> 3.904 | G29: =$C$23*G$17 -> 4.88 | H29: =$C$23*H$17 -> 4.88
A30: Initiative 2 benefit | B30: $M | C30: =SUM(D30:H30) -> 18.1475 | D30: =$C$24*D$17 -> 1.037 | E30: =$C$24*E$17 -> 2.5925 | F30: =$C$24*F$17 -> 4.148 | G30: =$C$24*G$17 -> 5.185 | H30: =$C$24*H$17 -> 5.185
A31: Initiative 3 benefit | B31: $M | C31: =SUM(D31:H31) -> 11.529 | D31: =$C$25*D$17 -> 0.6588 | E31: =$C$25*E$17 -> 1.647 | F31: =$C$25*F$17 -> 2.6352 | G31: =$C$25*G$17 -> 3.294 | H31: =$C$25*H$17 -> 3.294
A32: Total benefit | B32: $M | C32: =SUM(D32:H32) -> 46.7565 | D32: =SUM(D29:D31) -> 2.6718 | E32: =SUM(E29:E31) -> 6.6795 | F32: =SUM(F29:F31) -> 10.6872 | G32: =SUM(G29:G31) -> 13.359 | H32: =SUM(H29:H31) -> 13.359
A33: One-time cost | B33: $M | C33: =SUM(D33:H33) -> -6 | D33: =-$C$15*D18 -> -3.6 | E33: =-$C$15*E18 -> -2.4 | F33: =-$C$15*F18 -> 0 | G33: =-$C$15*G18 -> 0 | H33: =-$C$15*H18 -> 0
A34: Net cash flow | B34: $M | C34: =SUM(D34:H34) -> 40.7565 | D34: =D32+D33 -> -0.9282 | E34: =E32+E33 -> 4.2795 | F34: =F32+F33 -> 10.6872 | G34: =G32+G33 -> 13.359 | H34: =H32+H33 -> 13.359
A35: Discount factor | B35: x | D35: =1/(1+$C$16)^D$5 -> 0.90909091 | E35: =1/(1+$C$16)^E$5 -> 0.82644628 | F35: =1/(1+$C$16)^F$5 -> 0.7513148 | G35: =1/(1+$C$16)^G$5 -> 0.68301346 | H35: =1/(1+$C$16)^H$5 -> 0.62092132
A36: Present value | B36: $M | C36: =SUM(D36:H36) -> 28.141675 | D36: =D34*D35 -> -0.84381818 | E36: =E34*E35 -> 3.5367769 | F36: =F34*F35 -> 8.0294515 | G36: =G34*G35 -> 9.1243768 | H36: =H34*H35 -> 8.294888
A37: Cumulative net cash flow | B37: $M | D37: =SUM($D34:D34) -> -0.9282 | E37: =SUM($D34:E34) -> 3.3513 | F37: =SUM($D34:F34) -> 14.0385 | G37: =SUM($D34:G34) -> 27.3975 | H37: =SUM($D34:H34) -> 40.7565
A38: Cumulative positive flag | B38: flag | C38: =IF(SUM(D38:H38)=0,"Not within horizon",COUNT(D5:H5)-SUM(D38:H38)+1) -> 2 | D38: =IF(D37>=0,1,0) -> 0 | E38: =IF(E37>=0,1,0) -> 1 | F38: =IF(F37>=0,1,0) -> 1 | G38: =IF(G37>=0,1,0) -> 1 | H38: =IF(H37>=0,1,0) -> 1
A39: Payback year assumes cumulative cash stays positive once it turns positive. Check row 37 if costs recur.

Sheet Scenarios
A1: Scenarios
A2: Pick the active scenario. Inputs tab pulls the matching column.
A4: Active scenario | C4: Base
A5: Scenario index (1=Low, 2=Base, 3=High) | C5: =MATCH(C4,B8:B10,0) -> 2
A7: Index | B7: Scenario | C7: Definition
A8: 1 | B8: Low | C8: Conservative: lower uplift, higher one-time cost. Use for downside and finance haircut view.
A9: 2 | B9: Base | C9: Most likely: benchmark-backed uplift, planned one-time cost.
A10: 3 | B10: High | C10: Stretch: top-quartile uplift, lower one-time cost.
A12: To record results from each scenario: switch C4, copy the Outputs values, paste-as-values into the Log tab with date and version. Do not leave pasted values inside calculation tabs.

Sheet Outputs
A1: Outputs
A2: Everything the slides use. Slide references must match the 'Used on slide(s)' column.
A4: Output | B4: Unit | C4: Value | D4: Used on slide(s) | E4: Definition
A5: Baseline EBITDA | B5: $M | C5: =Calc!C21 -> 91.5 | D5: [slide #] | E5: Revenue x baseline margin; ties to client-reported EBITDA
A6: Initiative 1 run-rate EBITDA | B6: $M | C6: =Calc!C23 -> 4.88 | D6: [slide #] | E6: Revenue uplift x flow-through
A7: Initiative 2 run-rate EBITDA | B7: $M | C7: =Calc!C24 -> 5.185 | D7: [slide #] | E7: Cost reduction % x baseline cost base
A8: Initiative 3 run-rate EBITDA | B8: $M | C8: =Calc!C25 -> 3.294 | D8: [slide #] | E8: Price realization x flow-through
A9: Total run-rate uplift | B9: $M | C9: =Calc!C26 -> 13.359 | D9: [slide #] | E9: Sum of initiatives at 100% ramp
A10: Target EBITDA (run-rate) | B10: $M | C10: =C5+C9 -> 104.859 | D10: [slide #] | E10: Baseline plus total uplift
A11: Year-5 total benefit | B11: $M | C11: =Calc!H32 -> 13.359 | D11: [slide #] | E11: Benefit in Y5 after ramp
A12: Total one-time cost | B12: $M | C12: =-Calc!C33 -> 6 | D12: [slide #] | E12: Sum of phased one-time cost
A13: NPV of net cash flow (5 years) | B13: $M | C13: =Calc!C36 -> 28.141675 | D13: [slide #] | E13: Discounted at the live discount rate; no terminal value
A14: Payback year | B14: year # | C14: =Calc!C38 -> 2 | D14: [slide #] | E14: First year cumulative net cash flow is positive
A16: Active scenario | C16: =Scenarios!C4 -> Base
A18: EBITDA bridge (feeds the waterfall chart)
A19: Step | B19: Unit | C19: Value
A20: Baseline EBITDA | B20: $M | C20: =C5 -> 91.5
A21: Initiative 1 | B21: $M | C21: =C6 -> 4.88
A22: Initiative 2 | B22: $M | C22: =C7 -> 5.185
A23: Initiative 3 | B23: $M | C23: =C8 -> 3.294
A24: Target EBITDA | B24: $M | C24: =SUM(C20:C23) -> 104.859
A26: Error cells in output block | C26: =SUMPRODUCT(--ISERROR(C5:C14))+SUMPRODUCT(--ISERROR(C20:C24)) -> 0

Sheet Checks
A1: Checks
A2: Integrity checks must be zero. Sense checks flag for review but do not necessarily mean an error. Green values are pulled in the block at the bottom.
B4: Tolerance ($M, linked) | C4: =Inputs!G11 -> 0.05
A6: # | B6: Check | C6: Difference | D6: Tolerance | F6: Flag | G6: What to do if flagged
A7: 1 | B7: Baseline EBITDA ties to client-reported | C7: =ABS(C29-C30) -> 0 | D7: =$C$4 -> 0.05 | F7: =IF(C7>D7,1,0) -> 0 | G7: Reconcile revenue and margin to the ledger
A8: 2 | B8: Bridge target equals target output | C8: =ABS(C31-C32) -> 0 | D8: =$C$4 -> 0.05 | F8: =IF(C8>D8,1,0) -> 0 | G8: Check Outputs bridge rows
A9: 3 | B9: Initiative benefits sum to total benefit | C9: =ABS(C33-(C34+C35+C36)) -> 0 | D9: =$C$4 -> 0.05 | F9: =IF(C9>D9,1,0) -> 0 | G9: Check Calc rows 29-32
A10: 4 | B10: One-time cost phasing sums to 100% | C10: =ABS(C37-1) -> 0 | D10: 0.0001 | F10: =IF(C10>D10,1,0) -> 0 | G10: Fix Inputs T2
A11: 5 | B11: Ramp-up never exceeds 100% | C11: =MAX(0,C38-1) -> 0 | D11: 0.0001 | F11: =IF(C11>D11,1,0) -> 0 | G11: Fix Inputs T1
A12: 6 | B12: Scenario index is valid | C12: =IF(ISNUMBER(C39),0,1) -> 0 | D12: 0 | F12: =IF(C12>D12,1,0) -> 0 | G12: Pick Low, Base, or High on Scenarios
A13: 7 | B13: No error values in outputs | C13: =C42 -> 0 | D13: 0 | F13: =IF(C13>D13,1,0) -> 0 | G13: Trace the error on Outputs
A15: Sense checks (rules of thumb; review, do not auto-fail)
A16: # | B16: Check | C16: Value | D16: Min / Max | F16: Flag | G16: Comment
A17: 1 | B17: Year-5 benefit as % of baseline EBITDA (max) | C17: =C40/C29 -> 0.146 | D17: 0.25 | F17: =IF(C17>D17,1,0) -> 0 | G17: Above band: re-test the biggest driver
A18: 2 | B18: Baseline EBITDA margin within plausible band (min / max) | C18: =C41 -> 0.15 | D18: 0.05 | E18: 0.4 | F18: =IF(OR(C18<D18,C18>E18),1,0) -> 0 | G18: Outside peer range: confirm the input
A20: Master check
B21: Integrity flags (must be 0) | C21: =SUM(F7:F13) -> 0
B22: Sense-check flags (review) | C22: =SUM(F17:F18) -> 0
A28: Linked values used above (green = pulled from other tabs)
B29: Baseline EBITDA (model) | C29: =Calc!C21 -> 91.5
B30: Client-reported baseline EBITDA | C30: =Inputs!G10 -> 91.5
B31: Bridge target | C31: =Outputs!C24 -> 104.859
B32: Target EBITDA output | C32: =Outputs!C10 -> 104.859
B33: Total benefit, all years | C33: =Calc!C32 -> 46.7565
B34: Initiative 1 benefit, all years | C34: =Calc!C29 -> 17.08
B35: Initiative 2 benefit, all years | C35: =Calc!C30 -> 18.1475
B36: Initiative 3 benefit, all years | C36: =Calc!C31 -> 11.529
B37: Cost phasing total | C37: =Inputs!I23 -> 1
B38: Ramp-up maximum | C38: =Inputs!I22 -> 1
B39: Scenario index | C39: =Scenarios!C5 -> 2
B40: Year-5 total benefit | C40: =Calc!H32 -> 13.359
B41: Baseline EBITDA margin | C41: =Inputs!G9 -> 0.15
B42: Error cells in outputs | C42: =Outputs!C26 -> 0

Sheet Log
A1: Log
A2: Version log, data log, open issues, and review sign-off.
A4: Version | B4: Date | C4: By | D4: Change | E4: Status
A5: v0.1 | B5: 2026-10-16 | C5: OS | D5: Starter template created: example opportunity model with checks and scenarios | E5: Template
A8: Data log
A9: File / pull | B9: Received | C9: From | D9: Permission basis and storage location | E9: Sensitivity
A14: Open issues
A15: ID | B15: Raised | C15: Owner | D15: Issue | E15: Status
A20: Review sign-off
A21: Method | B21: Date | C21: Reviewer | D21: Findings and resolution | E21: Result
A22: Inputs vs sources
A23: Formulas
A24: Outputs vs benchmark
A25: Back-of-envelope
A26: Standards
